Neuron/__init__.py
Neuron/perceptron.py
Neuron_pypi_RajanAiden-0.0.2.dist-info/LICENSE
Neuron_pypi_RajanAiden-0.0.2.dist-info/METADATA
Neuron_pypi_RajanAiden-0.0.2.dist-info/WHEEL
Neuron_pypi_RajanAiden-0.0.2.dist-info/top_level.txt
Neuron_pypi_RajanAiden-0.0.2.dist-info/RECORD
